{
  "name": "io.github.slookisen/lokal",
  "description": "A2A marketplace for local food in Norway. Search 1,400+ farms, markets, and shops across 100+ Norwegian cities. Returns ranked producers with contact info, trust scores, and vCard links.",
  "version": "0.2.0",
  "packages": [
    {
      "registry_type": "npm",
      "name": "lokal-mcp",
      "version": "0.2.0"
    }
  ],
  "repository": {
    "url": "https://github.com/slookisen/lokal",
    "source": "github"
  },
  "remoteEndpoints": [
    {
      "transportType": "streamablehttp",
      "url": "https://rettfrabonden.com/mcp"
    }
  ]
}
